autovar/__init__.py
autovar/auto_var.py
autovar/base/__init__.py
autovar/base/decorators.py
autovar/hooks/__init__.py
autovar/tests/__init__.py
autovar/tests/test_autovar.py
autovar/utils/__init__.py
autovar-0.0.1a3.dist-info/METADATA
autovar-0.0.1a3.dist-info/WHEEL
autovar-0.0.1a3.dist-info/top_level.txt
autovar-0.0.1a3.dist-info/RECORD
