Metadata-Version: 2.1
Name: autovar
Version: 0.0.1a3
Summary: Experiment variables management framework.
Home-page: https://github.com/yangarbiter/autovar/
Author: Yao-Yuan Yang
Author-email: yangarbiter@gmail.com
License: UNKNOWN
Platform: UNKNOWN
Classifier: Development Status :: 3 - Alpha
Requires-Dist: numpy
Requires-Dist: pandas
Requires-Dist: scikit-learn
Requires-Dist: requests
Requires-Dist: gitpython
Requires-Dist: mkdir-p
Requires-Dist: joblib
Provides-Extra: dev
Requires-Dist: pylint ; extra == 'dev'
Provides-Extra: test
Requires-Dist: coverage ; extra == 'test'
Requires-Dist: pylint ; extra == 'test'
Requires-Dist: mypy ; extra == 'test'
